raimitigations/__init__.py
raimitigations/cohort/__init__.py
raimitigations/cohort/cohort_definition.py
raimitigations/cohort/cohort_handler.py
raimitigations/cohort/cohort_manager.py
raimitigations/cohort/utils.py
raimitigations/cohort/decoupled_class/__init__.py
raimitigations/cohort/decoupled_class/decoupled_classifier.py
raimitigations/cohort/decoupled_class/decoupled_cohort.py
raimitigations/cohort/decoupled_class/decoupled_utils.py
raimitigations/databalanceanalysis/__init__.py
raimitigations/databalanceanalysis/aggregate_measures.py
raimitigations/databalanceanalysis/balance_measure.py
raimitigations/databalanceanalysis/balance_metric_functions.py
raimitigations/databalanceanalysis/constants.py
raimitigations/databalanceanalysis/distribution_measures.py
raimitigations/databalanceanalysis/feature_measures.py
raimitigations/dataprocessing/__init__.py
raimitigations/dataprocessing/data_processing.py
raimitigations/dataprocessing/encoder/__init__.py
raimitigations/dataprocessing/encoder/encoder.py
raimitigations/dataprocessing/encoder/ohe.py
raimitigations/dataprocessing/encoder/ordinal.py
raimitigations/dataprocessing/feat_selection/__init__.py
raimitigations/dataprocessing/feat_selection/catboost_select.py
raimitigations/dataprocessing/feat_selection/correlated_features.py
raimitigations/dataprocessing/feat_selection/selector.py
raimitigations/dataprocessing/feat_selection/sequential_select.py
raimitigations/dataprocessing/imputer/__init__.py
raimitigations/dataprocessing/imputer/basic_imputer.py
raimitigations/dataprocessing/imputer/imputer.py
raimitigations/dataprocessing/imputer/iterative_imputer.py
raimitigations/dataprocessing/imputer/knn_imputer.py
raimitigations/dataprocessing/sampler/__init__.py
raimitigations/dataprocessing/sampler/rebalance.py
raimitigations/dataprocessing/sampler/synthesizer.py
raimitigations/dataprocessing/scaler/__init__.py
raimitigations/dataprocessing/scaler/minmax.py
raimitigations/dataprocessing/scaler/normalizer.py
raimitigations-1.1.1.dist-info/LICENSE
raimitigations-1.1.1.dist-info/METADATA
raimitigations-1.1.1.dist-info/WHEEL
raimitigations-1.1.1.dist-info/top_level.txt
raimitigations-1.1.1.dist-info/RECORD
