Metadata-Version: 2.1
Name: raimitigations
Version: 1.1.1
Summary: Python library for implementing and exploring mitigations for Responsible AI.
Home-page: https://github.com/microsoft/responsible-ai-toolbox-mitigations
Author: Matheus Mendonça, Marah Abdin, Dany Rouhana
Author-email: rai-toolbox@microsoft.com
License: MIT License
Classifier: Programming Language :: Python :: 3.7
Classifier: Programming Language :: Python :: 3.8
Classifier: Programming Language :: Python :: 3.9
Classifier: Programming Language :: Python :: 3.10
Classifier: Operating System :: OS Independent
License-File: LICENSE
Requires-Dist: numpy
Requires-Dist: pandas
Requires-Dist: seaborn
Requires-Dist: scipy
Requires-Dist: scikit-learn
Requires-Dist: imbalanced-learn (<=0.9.1)
Requires-Dist: sdv (==0.18.0)
Requires-Dist: mlxtend
Requires-Dist: researchpy
Requires-Dist: catboost
Requires-Dist: statsmodels
Requires-Dist: xgboost
Requires-Dist: raiutils
Provides-Extra: all
Requires-Dist: Jupyter ; extra == 'all'
Requires-Dist: uci-dataset ; extra == 'all'
Requires-Dist: seaborn ; extra == 'all'
Requires-Dist: feature-engine ; extra == 'all'
Provides-Extra: dev
Requires-Dist: Jupyter ; extra == 'dev'
Requires-Dist: uci-dataset ; extra == 'dev'
Requires-Dist: seaborn ; extra == 'dev'
Requires-Dist: feature-engine ; extra == 'dev'
Requires-Dist: pre-commit ; extra == 'dev'
Requires-Dist: configparser ; extra == 'dev'
Requires-Dist: semver ; extra == 'dev'
Requires-Dist: wheel (>=0.38.1) ; extra == 'dev'
Requires-Dist: build ; extra == 'dev'
Requires-Dist: pytest ; extra == 'dev'
Requires-Dist: pytest-codecov ; extra == 'dev'
Requires-Dist: pytest-json-report ; extra == 'dev'
Requires-Dist: pytest-html ; extra == 'dev'
Requires-Dist: sphinx ; extra == 'dev'
Requires-Dist: sphinx-rtd-theme (>=1.1.1) ; extra == 'dev'
Requires-Dist: nbsphinx ; extra == 'dev'
Requires-Dist: nbconvert (>=6.5.1) ; extra == 'dev'
Requires-Dist: sphinx-gallery (==0.10.1) ; extra == 'dev'
Requires-Dist: nbstripout ; extra == 'dev'
Requires-Dist: nbformat ; extra == 'dev'
Requires-Dist: docutils (<=0.17.1) ; extra == 'dev'
